{
  "248213310787289099": {
    "prefix": "/",
    "channels": {
      "welcome": "676864274215206913",
      "nsAdminLogs": "400433365163048970",
      "suggestions": "406434459328577536",
      "hr": "248494008576376832",
      "reports": "348905488269705218"
    },
    "adminRoles": [
      "HR"
    ],
    "firstReportMessageId": "677639162337296395",
    "firstSuggestionMessageId": "509519842374844427"
  },
  "675157013650735115": {
    "prefix": "/",
    "channels": {
      "welcome": "676571256002183168",
      "nsAdminLogs": "676571311329509402",
      "suggestions": "676571353389858826",
      "hr": "676857245404889160",
      "reports": "676857525039005717"
    },
    "adminRoles": [
      "HR"
    ],
    "firstReportMessageId": "677641515564138506",
    "firstSuggestionMessageId": "678302282848272404"
  }
}
